odoo/addons/so_report_hide_salesperson/README.rst
odoo/addons/so_report_hide_salesperson/__init__.py
odoo/addons/so_report_hide_salesperson/__manifest__.py
odoo/addons/so_report_hide_salesperson/reports/sale_report_templates.xml
odoo/addons/so_report_hide_salesperson/static/description/icon.png
odoo_addon_so_report_hide_salesperson-15.0.1.0.0.2.dist-info/METADATA
odoo_addon_so_report_hide_salesperson-15.0.1.0.0.2.dist-info/WHEEL
odoo_addon_so_report_hide_salesperson-15.0.1.0.0.2.dist-info/top_level.txt
odoo_addon_so_report_hide_salesperson-15.0.1.0.0.2.dist-info/RECORD
